sopel_diagnosis/__init__.py
sopel_diagnosis/plugin.py
sopel_diagnosis-0.1.0.dist-info/COPYING
sopel_diagnosis-0.1.0.dist-info/METADATA
sopel_diagnosis-0.1.0.dist-info/WHEEL
sopel_diagnosis-0.1.0.dist-info/entry_points.txt
sopel_diagnosis-0.1.0.dist-info/top_level.txt
sopel_diagnosis-0.1.0.dist-info/RECORD
